claude_reviewer/__init__.py
claude_reviewer/cli.py
claude_reviewer/database.py
claude_reviewer/git_ops.py
claude_reviewer/models.py
claude_reviewer-0.3.9.dist-info/METADATA
claude_reviewer-0.3.9.dist-info/WHEEL
claude_reviewer-0.3.9.dist-info/entry_points.txt
claude_reviewer-0.3.9.dist-info/top_level.txt
claude_reviewer-0.3.9.dist-info/RECORD
