Metadata-Version: 2.4
Name: claude-reviewer
Version: 0.3.9
Summary: Local PR review system for Claude Code - GitHub-style code review without leaving your terminal
Author: Ben Bowles
License: MIT
Project-URL: Homepage, https://github.com/bowlesb/claude-reviewer
Project-URL: Documentation, https://github.com/bowlesb/claude-reviewer#readme
Project-URL: Repository, https://github.com/bowlesb/claude-reviewer
Project-URL: Issues, https://github.com/bowlesb/claude-reviewer/issues
Keywords: code-review,pull-request,git,cli,claude,ai,developer-tools
Classifier: Development Status :: 4 - Beta
Classifier: Environment :: Console
Classifier: Intended Audience :: Developers
Classifier: License :: OSI Approved :: MIT License
Classifier: Operating System :: OS Independent
Classifier: Programming Language :: Python :: 3
Classifier: Programming Language :: Python :: 3.9
Classifier: Programming Language :: Python :: 3.10
Classifier: Programming Language :: Python :: 3.11
Classifier: Programming Language :: Python :: 3.12
Classifier: Topic :: Software Development :: Version Control :: Git
Classifier: Topic :: Software Development :: Quality Assurance
Requires-Python: >=3.9
Requires-Dist: click>=8.0.0
Requires-Dist: gitpython>=3.1.0
Requires-Dist: rich>=13.0.0
Provides-Extra: dev
Requires-Dist: pytest>=7.0.0; extra == "dev"
Requires-Dist: pytest-cov>=4.0.0; extra == "dev"
Requires-Dist: pytest-mock>=3.12.0; extra == "dev"
Requires-Dist: mypy>=1.8.0; extra == "dev"
Requires-Dist: black>=24.0.0; extra == "dev"
Requires-Dist: isort>=5.13.0; extra == "dev"
Requires-Dist: autoflake>=2.2.0; extra == "dev"
Requires-Dist: ruff>=0.1.0; extra == "dev"
